coin_algorithm/__init__.py
coin_algorithm/domain/__init__.py
coin_algorithm/domain/bar.py
coin_algorithm/domain/bar_series.py
coin_algorithm/domain/base_bot.py
coin_algorithm/domain/bot_config.py
coin_algorithm/domain/bot_order_type.py
coin_algorithm/domain/chart.py
coin_algorithm/domain/coin_info.py
coin_algorithm/domain/plot.py
coin_algorithm/domain/signal.py
coin_algorithm/domain/time_travel.py
coin_algorithm/domain/trade_metadata.py
coin_algorithm/example/__init__.py
coin_algorithm/example/main.py
coin_algorithm/example/bot/__init__.py
coin_algorithm/example/bot/my_simple_bot.py
coin_algorithm/server/__init__.py
coin_algorithm/server/back_test_server.py
coin_algorithm/server/binance_server.py
coin_algorithm/service/__init__.py
coin_algorithm/service/back_test_data.py
coin_algorithm/service/back_test_service.py
coin_algorithm/service/binance_service.py
coin_algorithm/service/exchange/__init__.py
coin_algorithm/service/exchange/binance/__init__.py
coin_algorithm/service/exchange/binance/binance_future_connector.py
coin_algorithm/service/grpc/__init__.py
coin_algorithm/service/grpc/coin_service_pb2.py
coin_algorithm/service/grpc/coin_service_pb2_grpc.py
coin_algorithm-1.4.dist-info/METADATA
coin_algorithm-1.4.dist-info/WHEEL
coin_algorithm-1.4.dist-info/licenses/LICENSE
coin_algorithm-1.4.dist-info/RECORD
