Metadata-Version: 2.3
Name: coin-algorithm
Version: 1.4
Summary:  A codetotrade.app python client
Project-URL: homepage, https://codetotrade.app
Project-URL: documentation, https://docs.codetotrade.app
Project-URL: repository, https://github.com/truongnhukhang/codetotrade-python-client
Author-email: Khang Truong <truongnhukhang1993@gmail.com>
License:                                  Apache License
License-File: LICENSE
Keywords: client,codetotrade.app,coin-algorithm,python
Requires-Python: >=3.11
Requires-Dist: binance-futures-connector==4.0.0
Requires-Dist: grpcio==1.66.0
Requires-Dist: protobuf==5.27.2
